LICENSE
MANIFEST.in
README.rst
requirements.txt
setup.py
src/hostnamed/__init__.py
src/hostnamed/admin.py
src/hostnamed/apps.py
src/hostnamed/models.py
src/hostnamed/tests.py
src/hostnamed/urls.py
src/hostnamed/utils.py
src/hostnamed/views.py
src/hostnamed.egg-info/PKG-INFO
src/hostnamed.egg-info/SOURCES.txt
src/hostnamed.egg-info/dependency_links.txt
src/hostnamed.egg-info/not-zip-safe
src/hostnamed.egg-info/requires.txt
src/hostnamed.egg-info/top_level.txt
src/hostnamed/locale/zh_Hans/LC_MESSAGES/django.mo
src/hostnamed/locale/zh_Hans/LC_MESSAGES/django.po
src/hostnamed/migrations/0001_initial.py
src/hostnamed/migrations/__init__.py
src/scripts/hostname-ctrl
src/scripts/hostname-ctrl.py