Metadata-Version: 1.1
Name: hostnamed
Version: 0.1.5
Summary: Dynamic hostname manage and update.
Home-page: https://github.com/appstore-zencore/hostnamed
Author: zencore
Author-email: appstore@zencore.cn
License: MIT
Keywords: hostnamed
Platform: UNKNOWN
Classifier: Development Status :: 5 - Production/Stable
Classifier: Intended Audience :: Developers
Classifier: Topic :: Software Development :: Libraries :: Python Modules
Classifier: License :: OSI Approved :: MIT License
Classifier: Programming Language :: Python :: 3
Classifier: Programming Language :: Python :: 3 :: Only
Requires: django
Requires: zencore_django
Requires: zencore_utils
Requires: click
Requires: requests
